Metadata-Version: 2.1
Name: djrunner
Version: 1.0.2
Summary: Django run app
Home-page: https://github.com/pmaigutyak/djrunner
Author: Paul Maigutyak
Author-email: pmaigutyak@gmail.com
License: MIT
Download-URL: https://github.com/pmaigutyak/djrunner/archive/1.0.2.tar.gz
Platform: UNKNOWN
License-File: LICENSE
